{
  "updateTime": "2026-07-19T01:55:17.302Z",
  "avg": 3.97,
  "trend": 0.15,
  "trendAbs": 0.15,
  "days": [
    {
      "label": "6/20",
      "price": 3.93
    },
    {
      "label": "6/21",
      "price": 3.93
    },
    {
      "label": "6/22",
      "price": 3.93
    },
    {
      "label": "6/23",
      "price": 3.93
    },
    {
      "label": "6/24",
      "price": 3.93
    },
    {
      "label": "6/25",
      "price": 3.93
    },
    {
      "label": "6/26",
      "price": 3.93
    },
    {
      "label": "6/27",
      "price": 3.93
    },
    {
      "label": "6/28",
      "price": 3.93
    },
    {
      "label": "6/29",
      "price": 3.93
    },
    {
      "label": "6/30",
      "price": 3.93
    },
    {
      "label": "7/1",
      "price": 3.93
    },
    {
      "label": "7/2",
      "price": 3.93
    },
    {
      "label": "7/3",
      "price": 3.93
    },
    {
      "label": "7/4",
      "price": 3.93
    },
    {
      "label": "7/5",
      "price": 3.93
    },
    {
      "label": "7/6",
      "price": 3.93
    },
    {
      "label": "7/7",
      "price": 3.93
    },
    {
      "label": "7/8",
      "price": 3.93
    },
    {
      "label": "7/9",
      "price": 3.93
    },
    {
      "label": "7/10",
      "price": 3.93
    },
    {
      "label": "7/11",
      "price": 3.93
    },
    {
      "label": "7/12",
      "price": 3.93
    },
    {
      "label": "7/13",
      "price": 3.93
    },
    {
      "label": "7/14",
      "price": 3.97
    },
    {
      "label": "7/15",
      "price": 4.07
    },
    {
      "label": "7/16",
      "price": 4.18
    },
    {
      "label": "7/17",
      "price": 4.23
    },
    {
      "label": "7/18",
      "price": 4.19
    },
    {
      "label": "7/19",
      "price": 4.08
    }
  ]
}